JSGFToolsLeyzer/__init__.py
JSGFToolsLeyzer/deterministic_generator.py
JSGFToolsLeyzer/grammar.py
JSGFToolsLeyzer/parser.py
JSGFToolsLeyzer/probabilistic_generator.py
JSGFToolsLeyzer/utils.py
JSGFToolsLeyzer-0.2.0.dist-info/LICENSE
JSGFToolsLeyzer-0.2.0.dist-info/WHEEL
JSGFToolsLeyzer-0.2.0.dist-info/METADATA
JSGFToolsLeyzer-0.2.0.dist-info/RECORD
