Metadata-Version: 2.1
Name: JSGFToolsLeyzer
Version: 0.2.0
Summary: Tools for JSGF grammar expansion.
Author-email: cartesinus <msowansk@gmail.com>
Requires-Python: >=3.7
Classifier: Programming Language :: Python :: 3
Classifier: License :: OSI Approved :: MIT License
Classifier: Operating System :: OS Independent
Requires-Dist: pyparsing ~= 3.0.9
Project-URL: Bug Tracker, https://github.com/cartesinus/JSGFToolsLeyzer/issues
Project-URL: Homepage, https://github.com/cartesinus/JSGFToolsLeyzer
